geesefly/__init__.py
geesefly/geesefly.py
geesefly/skein.py
geesefly/threefish.py
geesefly/util.py
geesefly/util_numpy.py
geesefly-0.4.1.dist-info/DESCRIPTION.rst
geesefly-0.4.1.dist-info/METADATA
geesefly-0.4.1.dist-info/metadata.json
geesefly-0.4.1.dist-info/pbr.json
geesefly-0.4.1.dist-info/RECORD
geesefly-0.4.1.dist-info/top_level.txt
geesefly-0.4.1.dist-info/WHEEL
